Metadata-Version: 2.1
Name: jax-sparse
Version: 0.0.2
Summary: Efficient and Friendly Sparse Matrix Library for JAX.
Home-page: https://github.com/CrawlScript/jax-sparse
Author: Jun Hu
Author-email: hujunxianligong@gmail.com
License: GNU General Public License v3.0 (See LICENSE)
Platform: UNKNOWN
Requires-Python: >3.5.0
License-File: LICENSE
